byteapp_akt/__init__.py
byteapp_akt/__main__.py
byteapp_akt/cli.py
byteapp_akt/config.py
byteapp_akt/datasets.py
byteapp_akt/main.py
byteapp_akt/utils.py
byteapp_akt/api_debug/__init__.py
byteapp_akt/api_debug/local_debug.py
byteapp_akt/assets/__init__.py
byteapp_akt/assets/html/__init__.py
byteapp_akt/assets/html/akscript.html
byteapp_akt/assets/html/homepage.html
byteapp_akt/assets/images/__init__.py
byteapp_akt/assets/images/favicon.ico
byteapp_akt/core/__init__.py
byteapp_akt/core/api.py
byteapp_akt/database/__init__.py
byteapp_akt/database/connection.py
byteapp_akt/login/__init__.py
byteapp_akt/login/user_login.py
byteapp_akt/model/__init__.py
byteapp_akt/schema/__init__.py
byteapp_akt/schema/version.py
tests/__init__.py
tests/test_cli.py
tests/test_demo.py
byteapp_akt-0.0.87.1.1.dist-info/LICENSE
byteapp_akt-0.0.87.1.1.dist-info/METADATA
byteapp_akt-0.0.87.1.1.dist-info/WHEEL
byteapp_akt-0.0.87.1.1.dist-info/top_level.txt
byteapp_akt-0.0.87.1.1.dist-info/RECORD
