Metadata-Version: 2.1
Name: byteapp_akt
Version: 0.0.87.1.1
Summary: AKTools is a tool for AKShare HTTP API!
Home-page: https://github.com/akfamily/byteapp_akt
Author: AKFamily
Author-email: albertandking@gmail.com
License: MIT
Keywords: stock,option,futures,bond,index,air,others,finance,spider,quant,quantitative,investment,trading,algotrading
Classifier: Programming Language :: Python :: 3.8
Classifier: Programming Language :: Python :: 3.9
Classifier: Programming Language :: Python :: 3.10
Classifier: Programming Language :: Python :: 3.11
Classifier: Programming Language :: Python :: 3.12
Classifier: Programming Language :: Python :: 3.13
Classifier: License :: OSI Approved :: MIT License
Classifier: Operating System :: OS Independent
Requires-Python: >=3.8
License-File: LICENSE
Requires-Dist: byteapp-ak>=1.14.96
Requires-Dist: fastapi>=0.110.0
Requires-Dist: uvicorn>=0.16.0
Requires-Dist: python-multipart>=0.0.9
Requires-Dist: jinja2>=3.1.2
Requires-Dist: typer[all]>=0.6.1
